<?xml version="1.0" encoding="UTF-8"?>
<objects serializationModel="Studio.02.02.00">
	<object class="AudioFile" id="{e528ae1f-e68a-4787-ba47-98bcd6e44d35}">
		<property name="assetPath">
			<value>Phasmarine/SFX/Minigame/klokke klikk feil.wav</value>
		</property>
		<property name="frequencyInKHz">
			<value>44.0999985</value>
		</property>
		<property name="channelCount">
			<value>2</value>
		</property>
		<property name="length">
			<value>0.53471655328798184</value>
		</property>
		<relationship name="masterAssetFolder">
			<destination>{9ea293e2-bc9f-412e-a3d7-c0172cbd0c51}</destination>
		</relationship>
	</object>
</objects>
